{"nodes": [{"id": "admin_portal_src_modules_reports_store_reportsslice_ts", "label": "reportsSlice.ts", "file_type": "code", "source_file": "admin-portal\\src\\modules\\reports\\store\\reportsSlice.ts", "source_location": "L1"}], "edges": [{"source": "admin_portal_src_modules_reports_store_reportsslice_ts", "target": "toolkit", "relation": "imports_from", "confidence": "EXTRACTED", "source_file": "admin-portal\\src\\modules\\reports\\store\\reportsSlice.ts", "source_location": "L1", "weight": 1.0}, {"source": "admin_portal_src_modules_reports_store_reportsslice_ts", "target": "admin_portal_src_shared_types", "relation": "imports_from", "confidence": "EXTRACTED", "source_file": "admin-portal\\src\\modules\\reports\\store\\reportsSlice.ts", "source_location": "L2", "weight": 1.0}, {"source": "admin_portal_src_modules_reports_store_reportsslice_ts", "target": "admin_portal_src_modules_reports_services_reportsservice", "relation": "imports_from", "confidence": "EXTRACTED", "source_file": "admin-portal\\src\\modules\\reports\\store\\reportsSlice.ts", "source_location": "L3", "weight": 1.0}], "raw_calls": []}